setup.py
liang/__init__.py
liang.egg-info/PKG-INFO
liang.egg-info/SOURCES.txt
liang.egg-info/dependency_links.txt
liang.egg-info/not-zip-safe
liang.egg-info/top_level.txt