Metadata-Version: 1.0
Name: liang
Version: 0.0.2
Summary: only me
Home-page: https://github.com/fengfengxiong123/liang.git
Author: 梁峰
Author-email: 359975715@qq.com
License: MIT
Platform: UNKNOWN
